README
setup.py
pip_crate/__init__.py
pip_crate/__main__.py
pip_crate.egg-info/PKG-INFO
pip_crate.egg-info/SOURCES.txt
pip_crate.egg-info/dependency_links.txt
pip_crate.egg-info/entry_points.txt
pip_crate.egg-info/requires.txt
pip_crate.egg-info/top_level.txt