Metadata-Version: 1.1
Name: pip-crate
Version: 0.1
Summary: Simple pip wrapper that uses crate.io repository for better speed.
Home-page: https://github.com/pedrospdc/pip-crate
Author: Pedro Palhares
Author-email: pedrospdc@gmail.com
License: UNKNOWN
Platform: UNKNOWN
Classifier: Development Status :: 4 - Beta
Classifier: License :: OSI Approved :: MIT License
Classifier: Operating System :: OS Independent
